hungarian_stemmer/__init__.py
hungarian_stemmer/hungarian_stemmer.py
hungarian_stemmer/resources/hu_HU.aff
hungarian_stemmer/resources/hu_HU.dic
hungarian_stemmer-2022.1.dist-info/LICENSE
hungarian_stemmer-2022.1.dist-info/WHEEL
hungarian_stemmer-2022.1.dist-info/METADATA
hungarian_stemmer-2022.1.dist-info/RECORD
